doc/Makefile
doc/api.rst
doc/conf.py
doc/index.rst
doc/usage.rst
doc/whatsnew.rst
doc/_templates/autosummary/class.rst
doc/_templates/autosummary/module.rst
dsss/__init__.py
dsss/availability.py
dsss/common.py
dsss/config.py
dsss/data.py
dsss/metadata.py
dsss/py.typed
dsss/registration.py
dsss/schema.py
dsss/starlette.py
dsss/store.py
dsss/structure.py
dsss/testing.py
dsss/tests/__init__.py
dsss/tests/test_core.py
dsss/tests/test_store.py
dsss/tests/test_testing.py
dsss-1.3.0.dist-info/LICENSE
dsss-1.3.0.dist-info/METADATA
dsss-1.3.0.dist-info/WHEEL
dsss-1.3.0.dist-info/top_level.txt
dsss-1.3.0.dist-info/RECORD
