Metadata-Version: 2.1
Name: dsss
Version: 1.3.0
Summary: Dead-Simple SDMX Server
Author: DSSS contributors
Maintainer-email: Paul Natsuo Kishimoto <mail@paul.kishimoto.name>
Project-URL: Documentation, https://dsss.readthedocs.io
Project-URL: Repository, https://github.com/khaeru/dsss
Classifier: License :: OSI Approved :: GNU Affero General Public License v3
Classifier: Natural Language :: English
Classifier: Operating System :: OS Independent
Classifier: Programming Language :: Python
Classifier: Programming Language :: Python :: 3 :: Only
Classifier: Programming Language :: Python :: 3.9
Classifier: Programming Language :: Python :: 3.10
Classifier: Programming Language :: Python :: 3.11
Classifier: Programming Language :: Python :: 3.12
Classifier: Programming Language :: Python :: 3.13
Requires-Python: >=3.9
License-File: LICENSE
Requires-Dist: sdmx1 >=2.17.0
Requires-Dist: starlette
Provides-Extra: doc
Requires-Dist: sphinx-book-theme ; extra == 'doc'
Provides-Extra: git-store
Requires-Dist: GitPython ; extra == 'git-store'
Provides-Extra: tests
Requires-Dist: dsss[git-store] ; extra == 'tests'
Requires-Dist: pytest >=8 ; extra == 'tests'
Requires-Dist: pytest-cov ; extra == 'tests'
Requires-Dist: sdmx1[tests] ; extra == 'tests'
Requires-Dist: starlette[full] ; extra == 'tests'
